ibrut_user_agent/__init__.py
ibrut_user_agent/ibrut_user_agent.py
ibrut_user_agent-0.1.4.dist-info/LICENSE
ibrut_user_agent-0.1.4.dist-info/METADATA
ibrut_user_agent-0.1.4.dist-info/WHEEL
ibrut_user_agent-0.1.4.dist-info/top_level.txt
ibrut_user_agent-0.1.4.dist-info/RECORD
