Metadata-Version: 2.1
Name: ibrut_user_agent
Version: 0.1.4
Summary: Random instagram useragent app
Home-page: https://github.com/khamdihi-dev/ibrut_user_agent
Author: Khamdihi dev
Author-email: dihidev.id@gmail.com
License: MIT
Classifier: Programming Language :: Python :: 3.9
Classifier: Programming Language :: Python :: 3.10
Classifier: Programming Language :: Python :: 3.11
Classifier: Programming Language :: Python :: 3.12
Classifier: License :: OSI Approved :: MIT License
Classifier: Operating System :: OS Independent
Requires-Python: >=3.9
License-File: LICENSE
